OSCR_django_client/__init__.py
OSCR_django_client/api_client.py
OSCR_django_client/api_response.py
OSCR_django_client/configuration.py
OSCR_django_client/exceptions.py
OSCR_django_client/py.typed
OSCR_django_client/rest.py
OSCR_django_client/api/__init__.py
OSCR_django_client/api/combatlog_api.py
OSCR_django_client/api/ladder_api.py
OSCR_django_client/api/ladder_entries_api.py
OSCR_django_client/api/system_api.py
OSCR_django_client/api/variant_api.py
OSCR_django_client/models/__init__.py
OSCR_django_client/models/combat_log.py
OSCR_django_client/models/combat_log_upload_response.py
OSCR_django_client/models/combat_log_upload_v2_response.py
OSCR_django_client/models/combatlog_list200_response.py
OSCR_django_client/models/ladder.py
OSCR_django_client/models/ladder_entries_list200_response.py
OSCR_django_client/models/ladder_entry.py
OSCR_django_client/models/ladder_list200_response.py
OSCR_django_client/models/metadata.py
OSCR_django_client/models/update.py
OSCR_django_client/models/variant.py
OSCR_django_client/models/variant_list200_response.py
oscr_django_client-2025.3.29.0.dist-info/METADATA
oscr_django_client-2025.3.29.0.dist-info/WHEEL
oscr_django_client-2025.3.29.0.dist-info/top_level.txt
oscr_django_client-2025.3.29.0.dist-info/RECORD
